tts/__init__.py
tts/cli.py
tts/config.py
tts/repack.py
tts/savegame.py
tts/unpack.py
tts/workshop.py
tts/utils/__init__.py
tts/utils/cli.py
tts/utils/formats.py
tabletop_tools-0.7.1.dist-info/entry_points.txt
tabletop_tools-0.7.1.dist-info/LICENSE
tabletop_tools-0.7.1.dist-info/WHEEL
tabletop_tools-0.7.1.dist-info/METADATA
tabletop_tools-0.7.1.dist-info/RECORD
