Metadata-Version: 2.1
Name: tabletop-tools
Version: 0.7.1
Summary: Tools for interacting with Tabletop Simulator mods.
Author: Tom Prince
Author-email: tom.prince@hocat.ca
Requires-Python: >=3.7
Classifier: License :: OSI Approved :: Mozilla Public License 2.0 (MPL 2.0)
Requires-Dist: attrs
Requires-Dist: bson
Requires-Dist: cattrs
Requires-Dist: requests
Requires-Dist: toml
Project-URL: Repository, https://github.com/tomprince/tabletop-tools
